actyon/__init__.py
actyon/__meta__.py
actyon/actyon.py
actyon/console.py
actyon/exceptions.py
actyon/flux.py
actyon/hook.py
actyon/helpers/__init__.py
actyon/helpers/common.py
actyon/helpers/consumer.py
actyon/helpers/injector.py
actyon/helpers/log.py
actyon/helpers/producer.py
actyon/sm/__init__.py
actyon/sm/base.py
actyon/sm/machine.py
actyon/sm/state.py
tests/__init__.py
tests/sm/__init__.py
tests/sm/test_base.py
tests/sm/test_machine.py
tests/sm/test_state.py
actyon-0.3.1.dist-info/LICENSE
actyon-0.3.1.dist-info/METADATA
actyon-0.3.1.dist-info/WHEEL
actyon-0.3.1.dist-info/top_level.txt
actyon-0.3.1.dist-info/RECORD
