Metadata-Version: 2.1
Name: actyon
Version: 0.3.1
Summary: Actyon offers an async approach on a multiplexed flux pattern.
Home-page: https://github.com/neatc0der/actyon
Author: neatc0der
Author-email: 
License: MIT
Download-URL: https://github.com/neatc0der/actyon/archive/0.3.1.tar.gz
Keywords: actyon async multiplex flux statemachine
Platform: UNKNOWN
Classifier: Development Status :: 4 - Beta
Classifier: Intended Audience :: Developers
Classifier: Intended Audience :: Information Technology
Classifier: License :: OSI Approved :: MIT License
Classifier: Operating System :: OS Independent
Classifier: Programming Language :: Python :: 3
Classifier: Programming Language :: Python :: 3 :: Only
Classifier: Programming Language :: Python :: 3.8
Classifier: Programming Language :: Python :: 3.9
Requires-Python: >=3.8
Requires-Dist: attrs (==20.3.0)
Requires-Dist: typing-utils (==0.0.3)
Requires-Dist: colorama (==0.4.4)
Requires-Dist: progress (==1.5)
